.gitignore
HISTORY.txt
LICENSE
MANIFEST.in
README.rst
bootstrap.py
buildout.cfg
requirements.txt
setup.py
ruper_detector/__init__.py
ruper_detector/ruper.py
ruper_detector.egg-info/PKG-INFO
ruper_detector.egg-info/SOURCES.txt
ruper_detector.egg-info/dependency_links.txt
ruper_detector.egg-info/entry_points.txt
ruper_detector.egg-info/not-zip-safe
ruper_detector.egg-info/requires.txt
ruper_detector.egg-info/top_level.txt