Metadata-Version: 1.2
Name: ruper-detector
Version: 2.0.1
Summary: EITB Irratian Ruper Ordorikaren kantuen detektorea
Home-page: http://github.com/erral/ruper_detector
Author: Mikel Larreategi
Author-email: mlarreategi@codesyntax.com
License: GPLv2
Keywords: ruper eitb music parsing
Platform: UNKNOWN
Classifier: Development Status :: 5 - Production/Stable
Classifier: License :: OSI Approved :: GNU General Public License v2 (GPLv2)
Classifier: Programming Language :: Python :: 3.6
Classifier: Programming Language :: Python :: 3.7
Classifier: Programming Language :: Python :: 3.8
Requires-Python: >=3.6
